adfly/__init__.py
adfly/api.py
adfly_api-1.0.3.dist-info/LICENSE
adfly_api-1.0.3.dist-info/METADATA
adfly_api-1.0.3.dist-info/WHEEL
adfly_api-1.0.3.dist-info/top_level.txt
adfly_api-1.0.3.dist-info/RECORD
