Metadata-Version: 2.1
Name: adfly-api
Version: 1.0.3
Summary: Unofficial Adfly API wrapper
Home-page: https://github.com/modbender/adfly-api
Author: Yashas H R
Author-email: rameshmamathayashas@gmail.com
License: UNKNOWN
Platform: any
Classifier: Intended Audience :: Developers
Classifier: Operating System :: OS Independent
Classifier: Programming Language :: Python
Classifier: Programming Language :: Python :: 3
Classifier: Programming Language :: Python :: 3 :: Only
Classifier: Topic :: Software Development :: Libraries :: Python Modules
Requires-Python: >=3.5
Requires-Dist: httplib2
